CHANGES.txt
bootstrap.py
buildout.cfg
setup.py
src/lovely/__init__.py
src/lovely.tag.egg-info/PKG-INFO
src/lovely.tag.egg-info/SOURCES.txt
src/lovely.tag.egg-info/dependency_links.txt
src/lovely.tag.egg-info/namespace_packages.txt
src/lovely.tag.egg-info/not-zip-safe
src/lovely.tag.egg-info/requires.txt
src/lovely.tag.egg-info/top_level.txt
src/lovely/tag/README.txt
src/lovely/tag/SETUP.cfg
src/lovely/tag/__init__.py
src/lovely/tag/configure.zcml
src/lovely/tag/engine.py
src/lovely/tag/ftesting.zcml
src/lovely/tag/ftests.py
src/lovely/tag/index.py
src/lovely/tag/index.txt
src/lovely/tag/interfaces.py
src/lovely/tag/lovely.tag-configure.zcml
src/lovely/tag/lovely.tag.sampledata-configure.zcml
src/lovely/tag/sampledata.py
src/lovely/tag/sampledata.zcml
src/lovely/tag/stresstest.txt
src/lovely/tag/tag.py
src/lovely/tag/tagging.py
src/lovely/tag/tags.data
src/lovely/tag/tests.py
src/lovely/tag/users.data
src/lovely/tag/browser/README.txt
src/lovely/tag/browser/__init__.py
src/lovely/tag/browser/configure.zcml
src/lovely/tag/browser/engine.py
src/lovely/tag/browser/linkedtagcloud.pt
src/lovely/tag/browser/manage.pt
src/lovely/tag/browser/tag.py
src/lovely/tag/browser/tagcloud.pt
src/lovely/tag/generations/__init__.py
src/lovely/tag/generations/configure.zcml
src/lovely/tag/generations/evolve1.py
src/lovely/tag/generations/evolve2.py
src/lovely/tag/performance/1000.words
src/lovely/tag/performance/10000.words
src/lovely/tag/performance/19.words
src/lovely/tag/performance/250.words
src/lovely/tag/performance/40000.words
src/lovely/tag/performance/4857.words
src/lovely/tag/performance/__init__.py
src/lovely/tag/performance/app.py
src/lovely/tag/performance/configurator.py
src/lovely/tag/performance/configure.zcml
src/lovely/tag/performance/domain.txt
src/lovely/tag/performance/event.py
src/lovely/tag/performance/interfaces.py
src/lovely/tag/performance/pre.txt
src/lovely/tag/performance/protocol.txt
src/lovely/tag/performance/sampledata.py
src/lovely/tag/performance/searchtags.pt
src/lovely/tag/performance/views.py