Metadata-Version: 1.0
Name: lovely.tag
Version: 1.1.0
Summary: A tagging engine for Zope 3
Home-page: http://pypi.python.org/pypi/lovely.tag
Author: Lovely Systems
Author-email: office@lovelysystems.com
License: ZPL 2.1
Keywords: zope3 lovely tag cloud
Platform: UNKNOWN
Classifier: Development Status :: 5 - Production/Stable
Classifier: Environment :: Web Environment
Classifier: Intended Audience :: Developers
Classifier: License :: OSI Approved :: Zope Public License
Classifier: Programming Language :: Python
Classifier: Natural Language :: English
Classifier: Operating System :: OS Independent
Classifier: Topic :: Internet :: WWW/HTTP
Classifier: Framework :: Zope3
